swanheader/__init__.py
swanheader/_version.py
swanheader-2.0.1.data/data/share/jupyter/labextensions/@swan-cern/header/package.json
swanheader-2.0.1.data/data/share/jupyter/labextensions/@swan-cern/header/static/190.24785dcbec3e0cb4b60f.js
swanheader-2.0.1.data/data/share/jupyter/labextensions/@swan-cern/header/static/549.16b7594f88fc1d161442.js
swanheader-2.0.1.data/data/share/jupyter/labextensions/@swan-cern/header/static/775cd88adaac96671c10.png
swanheader-2.0.1.data/data/share/jupyter/labextensions/@swan-cern/header/static/821.1ec3772804e56e6dd773.js
swanheader-2.0.1.data/data/share/jupyter/labextensions/@swan-cern/header/static/821.1ec3772804e56e6dd773.js.LICENSE.txt
swanheader-2.0.1.data/data/share/jupyter/labextensions/@swan-cern/header/static/remoteEntry.f15862ee29fa7ef89d58.js
swanheader-2.0.1.data/data/share/jupyter/labextensions/@swan-cern/header/static/style.js
swanheader-2.0.1.data/data/share/jupyter/labextensions/@swan-cern/header/static/third-party-licenses.json
swanheader-2.0.1.data/data/share/jupyter/labextensions/@swan-cern/header/install.json
swanheader-2.0.1.dist-info/METADATA
swanheader-2.0.1.dist-info/WHEEL
swanheader-2.0.1.dist-info/RECORD
