Metadata-Version: 2.1
Name: swanheader
Version: 2.0.1
Summary: SWAN JupyterLab Header Bar
Project-URL: Homepage, https://github.com/swan-cern/jupyter-extensions
Project-URL: Bug Tracker, https://github.com/swan-cern/jupyter-extensions/issues
Project-URL: Repository, https://github.com/swan-cern/jupyter-extensions.git
Author: SWAN Team
License-Expression: AGPL-3.0
Classifier: Framework :: Jupyter
Classifier: Framework :: Jupyter :: JupyterLab
Classifier: Framework :: Jupyter :: JupyterLab :: 4
Classifier: Framework :: Jupyter :: JupyterLab :: Extensions
Classifier: Framework :: Jupyter :: JupyterLab :: Extensions :: Prebuilt
Classifier: License :: OSI Approved :: BSD License
Classifier: Programming Language :: Python
Classifier: Programming Language :: Python :: 3
Classifier: Programming Language :: Python :: 3.8
Classifier: Programming Language :: Python :: 3.9
Classifier: Programming Language :: Python :: 3.10
Classifier: Programming Language :: Python :: 3.11
Requires-Python: >=3.8
